AUTHORS.rst
CONTRIBUTING.rst
HISTORY.rst
LICENSE
MANIFEST.in
README.rst
setup.cfg
setup.py
docs/Makefile
docs/authors.rst
docs/conf.py
docs/contributing.rst
docs/history.rst
docs/index.rst
docs/installation.rst
docs/make.bat
docs/modules.rst
docs/python_neuron.rst
docs/readme.rst
docs/usage.rst
docs/_build/html/_static/ajax-loader.gif
docs/_build/html/_static/comment-bright.png
docs/_build/html/_static/comment-close.png
docs/_build/html/_static/comment.png
docs/_build/html/_static/down-pressed.png
docs/_build/html/_static/down.png
docs/_build/html/_static/file.png
docs/_build/html/_static/minus.png
docs/_build/html/_static/plus.png
docs/_build/html/_static/up-pressed.png
docs/_build/html/_static/up.png
python_neuron/__init__.py
python_neuron/cli.py
python_neuron/python_neuron.py
python_neuron.egg-info/PKG-INFO
python_neuron.egg-info/SOURCES.txt
python_neuron.egg-info/dependency_links.txt
python_neuron.egg-info/entry_points.txt
python_neuron.egg-info/not-zip-safe
python_neuron.egg-info/requires.txt
python_neuron.egg-info/top_level.txt
tests/test_python_neuron.py