Metadata-Version: 1.1
Name: python-neuron
Version: 0.2.0
Summary: Create your own neurons and send messages between them
Home-page: https://github.com/iris9112/python_neuron
Author: Isabel Cristina Ruiz Buriticá
Author-email: iris9112@gmail.com
License: MIT license
Keywords: python_neuron
Platform: UNKNOWN
Classifier: Development Status :: 2 - Pre-Alpha
Classifier: Intended Audience :: Developers
Classifier: License :: OSI Approved :: MIT License
Classifier: Natural Language :: English
Classifier: Programming Language :: Python :: 2
Classifier: Programming Language :: Python :: 2.7
Classifier: Programming Language :: Python :: 3
Classifier: Programming Language :: Python :: 3.4
Classifier: Programming Language :: Python :: 3.5
Classifier: Programming Language :: Python :: 3.6
